[
  {
    "id": "3d2bf964-e7b6-47c0-9cc3-c3eb4177597e",
    "data": [
      {
        "text": "Dog?",
        "userDefined": false
      }
    ],
    "isTemplate": false,
    "count": 0,
    "lang": "en",
    "updated": 0
  },
  {
    "id": "041b3cae-4e0d-4e5a-a267-ae6d9f4496ee",
    "data": [
      {
        "text": "Can I have a random dog?",
        "userDefined": false
      }
    ],
    "isTemplate": false,
    "count": 0,
    "lang": "en",
    "updated": 0
  },
  {
    "id": "e2de052f-03d5-4daf-a60d-b6d7b6286125",
    "data": [
      {
        "text": "Can I have a dog?",
        "userDefined": false
      }
    ],
    "isTemplate": false,
    "count": 0,
    "lang": "en",
    "updated": 0
  },
  {
    "id": "98815624-6526-4a49-bfee-ffecb683abcd",
    "data": [
      {
        "text": "Random dog",
        "userDefined": false
      }
    ],
    "isTemplate": false,
    "count": 0,
    "lang": "en",
    "updated": 0
  }
]