[
  {
    "id": "3287ca85-892b-4166-80d8-5027035a80f0",
    "data": [
      {
        "text": "what is beauty",
        "userDefined": false
      }
    ],
    "isTemplate": false,
    "count": 0,
    "lang": "en",
    "updated": 0
  },
  {
    "id": "00a96eda-ebe8-4efe-8800-bccffce523e9",
    "data": [
      {
        "text": "tell me what is beauty",
        "userDefined": false
      }
    ],
    "isTemplate": false,
    "count": 0,
    "lang": "en",
    "updated": 0
  },
  {
    "id": "62c8d130-832a-4560-8d5d-053dbaf0ab88",
    "data": [
      {
        "text": "define word beautiful",
        "userDefined": false
      }
    ],
    "isTemplate": false,
    "count": 0,
    "lang": "en",
    "updated": 0
  },
  {
    "id": "d85dc0e6-8995-484a-a27a-dc87f6d49c9d",
    "data": [
      {
        "text": "tell me what\u0027s beauty",
        "userDefined": false
      }
    ],
    "isTemplate": false,
    "count": 0,
    "lang": "en",
    "updated": 0
  },
  {
    "id": "18798452-d77b-40b5-aadf-31befed06f2e",
    "data": [
      {
        "text": "what\u0027s beauty",
        "userDefined": false
      }
    ],
    "isTemplate": false,
    "count": 0,
    "lang": "en",
    "updated": 0
  },
  {
    "id": "d813926d-7114-4b14-97a1-fa0933115848",
    "data": [
      {
        "text": "define the beautiful",
        "userDefined": false
      }
    ],
    "isTemplate": false,
    "count": 0,
    "lang": "en",
    "updated": 0
  },
  {
    "id": "be7430e5-5180-4996-b20e-f19522f28fe2",
    "data": [
      {
        "text": "define the beauty",
        "userDefined": false
      }
    ],
    "isTemplate": false,
    "count": 0,
    "lang": "en",
    "updated": 0
  }
]