[
  {
    "id": "f1073c50-9cde-4abd-9cce-40b3d3ebd9bd",
    "data": [
      {
        "text": "will you tell me what is imagination",
        "userDefined": false
      }
    ],
    "isTemplate": false,
    "count": 0,
    "lang": "en",
    "updated": 0
  },
  {
    "id": "f3389f7b-69ed-4ee1-96f9-fac27c308bc3",
    "data": [
      {
        "text": "tell me what is imagination",
        "userDefined": false
      }
    ],
    "isTemplate": false,
    "count": 0,
    "lang": "en",
    "updated": 0
  },
  {
    "id": "4d3977eb-5f8d-4c36-bd61-e6e7226b2c92",
    "data": [
      {
        "text": "will you please tell me what\u0027s imagination",
        "userDefined": false
      }
    ],
    "isTemplate": false,
    "count": 0,
    "lang": "en",
    "updated": 0
  },
  {
    "id": "3794b316-343e-4922-8878-806106a5fc4f",
    "data": [
      {
        "text": "tell me what\u0027s imagination",
        "userDefined": false
      }
    ],
    "isTemplate": false,
    "count": 0,
    "lang": "en",
    "updated": 0
  },
  {
    "id": "289c18b6-573e-4d7b-8eaf-b59734e55d9f",
    "data": [
      {
        "text": "define word imagination",
        "userDefined": false
      }
    ],
    "isTemplate": false,
    "count": 0,
    "lang": "en",
    "updated": 0
  },
  {
    "id": "e3d85962-c7f8-4249-a7a2-67273cb8db2f",
    "data": [
      {
        "text": "define the imagination",
        "userDefined": false
      }
    ],
    "isTemplate": false,
    "count": 0,
    "lang": "en",
    "updated": 0
  }
]